sandesh_py/__init__.py
sandesh_py/attachments.py
sandesh_py/mailer.py
sandesh_py/smtp.py
sandesh_py/types.py
sandesh.py-0.0.2.dist-info/LICENSE
sandesh.py-0.0.2.dist-info/METADATA
sandesh.py-0.0.2.dist-info/WHEEL
sandesh.py-0.0.2.dist-info/top_level.txt
sandesh.py-0.0.2.dist-info/RECORD
