Metadata-Version: 2.1
Name: sandesh.py
Version: 0.0.2
Summary: Basic implementaion of SMTP client using TCP communication with the SMTP server using the `socket` module.
Author: Sandesh Khadaka
Author-email: Sandesh Khadka <mail@khadkasandesh.com.np>
Project-URL: Homepage, https://github.com/sandeshkhadka/sandesh
Project-URL: Issues, https://github.com/sandeshkhadka/sandesh/issues
Classifier: Programming Language :: Python :: 3
Classifier: License :: OSI Approved :: MIT License
Classifier: Operating System :: OS Independent
Requires-Python: >=3.8
License-File: LICENSE
